README.md
setup.py
twcloud/__init__.py
twcloud/twcloud.py
twcloud.egg-info/PKG-INFO
twcloud.egg-info/SOURCES.txt
twcloud.egg-info/dependency_links.txt
twcloud.egg-info/entry_points.txt
twcloud.egg-info/requires.txt
twcloud.egg-info/top_level.txt