Metadata-Version: 2.1
Name: twcloud
Version: 0.1
Summary: Python package + CLI to generate word clouds of Twitter tweets.
Home-page: https://github.com/minimaxir/twcloud
Author: Max Woolf
Author-email: max@minimaxir.com
License: MIT
Keywords: wordcloud,data visualization,text cool stuff
Platform: UNKNOWN
Requires-Python: >=3.6
